nv_one_logger/api/README.md
nv_one_logger/api/__init__.py
nv_one_logger/api/config.py
nv_one_logger/api/one_logger_provider.py
nv_one_logger/api/recorder.py
nv_one_logger/api/telemetry_config.py
nv_one_logger/api/timed_span.py
nv_one_logger/core/README.md
nv_one_logger/core/__init__.py
nv_one_logger/core/attributes.py
nv_one_logger/core/event.py
nv_one_logger/core/exceptions.py
nv_one_logger/core/internal/__init__.py
nv_one_logger/core/internal/logging.py
nv_one_logger/core/internal/metric_summarizer.py
nv_one_logger/core/internal/multi_window_timer.py
nv_one_logger/core/internal/safe_execution.py
nv_one_logger/core/internal/singleton.py
nv_one_logger/core/internal/utils.py
nv_one_logger/core/internal/version.py
nv_one_logger/core/span.py
nv_one_logger/core/time.py
nv_one_logger/exporter/README.md
nv_one_logger/exporter/__init__.py
nv_one_logger/exporter/base_json_exporter.py
nv_one_logger/exporter/export_config_manager.py
nv_one_logger/exporter/exporter.py
nv_one_logger/exporter/exporter_config.py
nv_one_logger/exporter/file_exporter.py
nv_one_logger/exporter/internal/__init__.py
nv_one_logger/exporter/internal/record_type.py
nv_one_logger/exporter/logger_exporter.py
nv_one_logger/no_init.md
nv_one_logger/recorder/__init__.py
nv_one_logger/recorder/default_recorder.py
nv_one_logger_core-2.3.0.dist-info/LICENSE
nv_one_logger_core-2.3.0.dist-info/METADATA
nv_one_logger_core-2.3.0.dist-info/WHEEL
nv_one_logger_core-2.3.0.dist-info/RECORD
